polymorphism/__init__.py
polymorphism/helpers.py
polymorphism/types.py
polymorphism/typing.py
polymorphism-0.1.2.dist-info/LICENSE
polymorphism-0.1.2.dist-info/WHEEL
polymorphism-0.1.2.dist-info/METADATA
polymorphism-0.1.2.dist-info/RECORD
